Workbook

Sheet Payroll Entry
A1: Payroll Reporting by Pay Type | K1: For assistance, contact Support at support@smartpayllc.com or call 877-204-0489, Mon-Fri 8AM-8PM EST.
A3: Enter your Summary Information here | K3: Reporting Tips:
A4: Policyholder Name | K4: See common inclusion/exclusion rules on Inclusion-Exclusion Rules Worksheet.
A5: FEIN | G5: 830349436 | K5: Summary Information:
A6: Policy number | K6: Fill in Blue Fields to auto-fill Upload worksheet and reconcile payroll entries.
K7: Report Date: enter based on reporting frequency. Match Reporting Schedule in SmartPay.
G8: Enter each reporting period: | K8: Enter Gross Wages from payroll register/report for reconciliation purposes.
A9: Report date (check date or month-end) | G9: 45960 | K9: Payroll Data:
A10: Period start date | G10: 45931 | K10: Work In State: enter as two letter abbreviation; Class codes: include leading zeros.
A11: Period end date | G11: 45960 | K11: The total of all pay types entered should equal Gross Wages (unless there is a CA Med 125 deduction).
A12: Gross Wages (from Payroll Register) | K12: For any pay types not reported separately, include in the 'Regular Wages' column.
K13: If you have CA Med 125 deductions, subtract from the 'Regular Wages' Pay Type.
A14: RECONCILIATION | K14: Include any 1099 wages to be reported.
A15: Reported Gross Wages (From Payroll Data entered below) | G15: =SUM(F23:I522) | K15: Overtime: enter total overtime wages, not just the wages based on overtime rate differential.
A16: Difference - Gross Wages from Register less reported below | G16: =G12-G15 | K16: If reporting by Employee, use unique Employee Numbers for each employee.
A17: Difference - Upload worksheet less reported below | G17: =SUM('A - Upload'!K2:N501)-'Payroll Entry'!G15 | K17: If reporting by Class Code, copy Class Codes in the Employee Number column. (cannot be blank)
K18: Report owners and officers separately to apply capping/inclusion rules in SmartPay.
K19: Set up owners, officers in SmartPay (Employee Info) for capping/inclusion rules to be applied.
K20: This file supports up to 500 lines of payroll reporting.
A21: Enter your Payroll Data Below (see Reporting Tips on how to report)
A22: Employee Number | B22: Employee First Name (Optional) | C22: Employee Last Name (Optional) | D22: Work in State | E22: Class Code | F22: Regular Wages | G22: OT Wages Time and One Half | H22: OT Wages Double Time | I22: Other Excluded Wages
A23: 1 | B23: Michael A | C23: Ahrens | D23: CA | E23: 540321 | F23: 262.98 | G23: 742.19 | H23: 0
A24: 2 | B24: Michael A | C24: Ahrens | D24: CA | E24: 543221 | F24: 3059.6 | G24: 0 | H24: 0
A25: 3 | B25: Jesus 'Ricardo' | C25: Almaraz Cabrera | D25: CA | E25: 540321 | F25: 189.64 | G25: 0 | H25: 0
A26: 4 | B26: Jesus 'Ricardo' | C26: Almaraz Cabrera | D26: CA | E26: 548234 | F26: 184.63 | G26: 0 | H26: 0
A27: 5 | B27: Larry W | C27: Aranda | D27: CA | E27: 540321 | F27: 374.18 | G27: 0 | H27: 0
A28: 6 | B28: Larry W | C28: Aranda | D28: CA | E28: 543221 | F28: 1006.33 | G28: 32 | H28: 0
A29: 7 | B29: Corey D | C29: Arista | D29: CA | E29: 540321 | F29: 458.71 | G29: 50.86 | H29: 0
A30: 8 | B30: Richard | C30: Ayers | D30: CA | E30: 540321 | F30: 74.11 | G30: 0 | H30: 0
A31: 9 | B31: Richard | C31: Ayers | D31: CA | E31: 548234 | F31: 732.67 | G31: 0 | H31: 0
A32: 10 | B32: Susan G | C32: Barr | D32: CA | E32: 8810 | F32: 11865.4 | G32: 0 | H32: 0
A33: 11 | B33: John A | C33: Boito | D33: CA | E33: 540321 | F33: 3323.92 | G33: 0 | H33: 0
A34: 12 | B34: John A | C34: Boito | D34: CA | E34: 548234 | F34: 1997.44 | G34: 20.36 | H34: 0
... A122: 100 | B122: Eric J | C122: Zuniga | D122: CA | E122: 543221 | F122: 756.21 | G122: 0 | H122: 0
B124: GRAND | C124: TOTAL | F124: =SUM(F23:F122) | G124: =SUM(G23:G122) | H124: =SUM(H23:H122)

Sheet A - Upload
A1: Policyholder | B1: FEIN | C1: Report Date | D1: Period Start Date | E1: Period End Date | F1: Employee Number | G1: Employee First Name | H1: Employee Last Name | I1: State | J1: Class Code | K1: Regular Wages | L1: OT Wages Time and One Half | M1: OT Wages Double Time | N1: Other Excluded | O1: Reporter | P1: Template
A2: =IF($J2="","",'Payroll Entry'!$G$4) | B2: =IF($J2="","",'Payroll Entry'!$G$5) | C2: =IF($J2="","",'Payroll Entry'!$G$9) | D2: =IF($J2="","",'Payroll Entry'!$G$10) | E2: =IF($J2="","",'Payroll Entry'!$G$11) | F2: =IF('Payroll Entry'!A23="","",'Payroll Entry'!A23) | G2: =IF('Payroll Entry'!B23="","",'Payroll Entry'!B23) | H2: =IF('Payroll Entry'!C23="","",'Payroll Entry'!C23) | I2: =IF('Payroll Entry'!D23="","",'Payroll Entry'!D23) | J2: =IF('Payroll Entry'!$E23="","",'Payroll Entry'!E23) | K2: =IF('Payroll Entry'!$E23="","",'Payroll Entry'!F23) | L2: =IF('Payroll Entry'!$E23="","",'Payroll Entry'!G23) | M2: =IF('Payroll Entry'!$E23="","",'Payroll Entry'!H23) | N2: =IF('Payroll Entry'!$E23="","",'Payroll Entry'!I23) | O2: =IF($J2="","","Self Reporter") | P2: =IF($J2="","","Pay Types")
A3: =IF($J3="","",'Payroll Entry'!$G$4) | B3: =IF($J3="","",'Payroll Entry'!$G$5) | C3: =IF($J3="","",'Payroll Entry'!$G$9) | D3: =IF($J3="","",'Payroll Entry'!$G$10) | E3: =IF($J3="","",'Payroll Entry'!$G$11) | F3: =IF('Payroll Entry'!A24="","",'Payroll Entry'!A24) | G3: =IF('Payroll Entry'!B24="","",'Payroll Entry'!B24) | H3: =IF('Payroll Entry'!C24="","",'Payroll Entry'!C24) | I3: =IF('Payroll Entry'!D24="","",'Payroll Entry'!D24) | J3: =IF('Payroll Entry'!$E24="","",'Payroll Entry'!E24) | K3: =IF('Payroll Entry'!$E24="","",'Payroll Entry'!F24) | L3: =IF('Payroll Entry'!$E24="","",'Payroll Entry'!G24) | M3: =IF('Payroll Entry'!$E24="","",'Payroll Entry'!H24) | N3: =IF('Payroll Entry'!$E24="","",'Payroll Entry'!I24) | O3: =IF($J3="","","Self Reporter") | P3: =IF($J3="","","Pay Types")
A4: =IF($J4="","",'Payroll Entry'!$G$4) | B4: =IF($J4="","",'Payroll Entry'!$G$5) | C4: =IF($J4="","",'Payroll Entry'!$G$9) | D4: =IF($J4="","",'Payroll Entry'!$G$10) | E4: =IF($J4="","",'Payroll Entry'!$G$11) | F4: =IF('Payroll Entry'!A25="","",'Payroll Entry'!A25) | G4: =IF('Payroll Entry'!B25="","",'Payroll Entry'!B25) | H4: =IF('Payroll Entry'!C25="","",'Payroll Entry'!C25) | I4: =IF('Payroll Entry'!D25="","",'Payroll Entry'!D25) | J4: =IF('Payroll Entry'!$E25="","",'Payroll Entry'!E25) | K4: =IF('Payroll Entry'!$E25="","",'Payroll Entry'!F25) | L4: =IF('Payroll Entry'!$E25="","",'Payroll Entry'!G25) | M4: =IF('Payroll Entry'!$E25="","",'Payroll Entry'!H25) | N4: =IF('Payroll Entry'!$E25="","",'Payroll Entry'!I25) | O4: =IF($J4="","","Self Reporter") | P4: =IF($J4="","","Pay Types")
A5: =IF($J5="","",'Payroll Entry'!$G$4) | B5: =IF($J5="","",'Payroll Entry'!$G$5) | C5: =IF($J5="","",'Payroll Entry'!$G$9) | D5: =IF($J5="","",'Payroll Entry'!$G$10) | E5: =IF($J5="","",'Payroll Entry'!$G$11) | F5: =IF('Payroll Entry'!A26="","",'Payroll Entry'!A26) | G5: =IF('Payroll Entry'!B26="","",'Payroll Entry'!B26) | H5: =IF('Payroll Entry'!C26="","",'Payroll Entry'!C26) | I5: =IF('Payroll Entry'!D26="","",'Payroll Entry'!D26) | J5: =IF('Payroll Entry'!$E26="","",'Payroll Entry'!E26) | K5: =IF('Payroll Entry'!$E26="","",'Payroll Entry'!F26) | L5: =IF('Payroll Entry'!$E26="","",'Payroll Entry'!G25) | M5: =IF('Payroll Entry'!$E26="","",'Payroll Entry'!H26) | N5: =IF('Payroll Entry'!$E26="","",'Payroll Entry'!I26) | O5: =IF($J5="","","Self Reporter") | P5: =IF($J5="","","Pay Types")
A6: =IF($J6="","",'Payroll Entry'!$G$4) | B6: =IF($J6="","",'Payroll Entry'!$G$5) | C6: =IF($J6="","",'Payroll Entry'!$G$9) | D6: =IF($J6="","",'Payroll Entry'!$G$10) | E6: =IF($J6="","",'Payroll Entry'!$G$11) | F6: =IF('Payroll Entry'!A27="","",'Payroll Entry'!A27) | G6: =IF('Payroll Entry'!B27="","",'Payroll Entry'!B27) | H6: =IF('Payroll Entry'!C27="","",'Payroll Entry'!C27) | I6: =IF('Payroll Entry'!D27="","",'Payroll Entry'!D27) | J6: =IF('Payroll Entry'!$E27="","",'Payroll Entry'!E27) | K6: =IF('Payroll Entry'!$E27="","",'Payroll Entry'!F27) | L6: =IF('Payroll Entry'!$E27="","",'Payroll Entry'!G27) | M6: =IF('Payroll Entry'!$E27="","",'Payroll Entry'!H27) | N6: =IF('Payroll Entry'!$E27="","",'Payroll Entry'!I27) | O6: =IF($J6="","","Self Reporter") | P6: =IF($J6="","","Pay Types")
A7: =IF($J7="","",'Payroll Entry'!$G$4) | B7: =IF($J7="","",'Payroll Entry'!$G$5) | C7: =IF($J7="","",'Payroll Entry'!$G$9) | D7: =IF($J7="","",'Payroll Entry'!$G$10) | E7: =IF($J7="","",'Payroll Entry'!$G$11) | F7: =IF('Payroll Entry'!A28="","",'Payroll Entry'!A28) | G7: =IF('Payroll Entry'!B28="","",'Payroll Entry'!B28) | H7: =IF('Payroll Entry'!C28="","",'Payroll Entry'!C28) | I7: =IF('Payroll Entry'!D28="","",'Payroll Entry'!D28) | J7: =IF('Payroll Entry'!$E28="","",'Payroll Entry'!E28) | K7: =IF('Payroll Entry'!$E28="","",'Payroll Entry'!F28) | L7: =IF('Payroll Entry'!$E28="","",'Payroll Entry'!G28) | M7: =IF('Payroll Entry'!$E28="","",'Payroll Entry'!H28) | N7: =IF('Payroll Entry'!$E28="","",'Payroll Entry'!I28) | O7: =IF($J7="","","Self Reporter") | P7: =IF($J7="","","Pay Types")
A8: =IF($J8="","",'Payroll Entry'!$G$4) | B8: =IF($J8="","",'Payroll Entry'!$G$5) | C8: =IF($J8="","",'Payroll Entry'!$G$9) | D8: =IF($J8="","",'Payroll Entry'!$G$10) | E8: =IF($J8="","",'Payroll Entry'!$G$11) | F8: =IF('Payroll Entry'!A29="","",'Payroll Entry'!A29) | G8: =IF('Payroll Entry'!B29="","",'Payroll Entry'!B29) | H8: =IF('Payroll Entry'!C29="","",'Payroll Entry'!C29) | I8: =IF('Payroll Entry'!D29="","",'Payroll Entry'!D29) | J8: =IF('Payroll Entry'!$E29="","",'Payroll Entry'!E29) | K8: =IF('Payroll Entry'!$E29="","",'Payroll Entry'!F29) | L8: =IF('Payroll Entry'!$E29="","",'Payroll Entry'!G29) | M8: =IF('Payroll Entry'!$E29="","",'Payroll Entry'!H29) | N8: =IF('Payroll Entry'!$E29="","",'Payroll Entry'!I29) | O8: =IF($J8="","","Self Reporter") | P8: =IF($J8="","","Pay Types")
A9: =IF($J9="","",'Payroll Entry'!$G$4) | B9: =IF($J9="","",'Payroll Entry'!$G$5) | C9: =IF($J9="","",'Payroll Entry'!$G$9) | D9: =IF($J9="","",'Payroll Entry'!$G$10) | E9: =IF($J9="","",'Payroll Entry'!$G$11) | F9: =IF('Payroll Entry'!A30="","",'Payroll Entry'!A30) | G9: =IF('Payroll Entry'!B30="","",'Payroll Entry'!B30) | H9: =IF('Payroll Entry'!C30="","",'Payroll Entry'!C30) | I9: =IF('Payroll Entry'!D30="","",'Payroll Entry'!D30) | J9: =IF('Payroll Entry'!$E30="","",'Payroll Entry'!E30) | K9: =IF('Payroll Entry'!$E30="","",'Payroll Entry'!F30) | L9: =IF('Payroll Entry'!$E30="","",'Payroll Entry'!G30) | M9: =IF('Payroll Entry'!$E30="","",'Payroll Entry'!H30) | N9: =IF('Payroll Entry'!$E30="","",'Payroll Entry'!I30) | O9: =IF($J9="","","Self Reporter") | P9: =IF($J9="","","Pay Types")
A10: =IF($J10="","",'Payroll Entry'!$G$4) | B10: =IF($J10="","",'Payroll Entry'!$G$5) | C10: =IF($J10="","",'Payroll Entry'!$G$9) | D10: =IF($J10="","",'Payroll Entry'!$G$10) | E10: =IF($J10="","",'Payroll Entry'!$G$11) | F10: =IF('Payroll Entry'!A31="","",'Payroll Entry'!A31) | G10: =IF('Payroll Entry'!B31="","",'Payroll Entry'!B31) | H10: =IF('Payroll Entry'!C31="","",'Payroll Entry'!C31) | I10: =IF('Payroll Entry'!D31="","",'Payroll Entry'!D31) | J10: =IF('Payroll Entry'!$E31="","",'Payroll Entry'!E31) | K10: =IF('Payroll Entry'!$E31="","",'Payroll Entry'!F31) | L10: =IF('Payroll Entry'!$E31="","",'Payroll Entry'!G31) | M10: =IF('Payroll Entry'!$E31="","",'Payroll Entry'!H31) | N10: =IF('Payroll Entry'!$E31="","",'Payroll Entry'!I31) | O10: =IF($J10="","","Self Reporter") | P10: =IF($J10="","","Pay Types")
A11: =IF($J11="","",'Payroll Entry'!$G$4) | B11: =IF($J11="","",'Payroll Entry'!$G$5) | C11: =IF($J11="","",'Payroll Entry'!$G$9) | D11: =IF($J11="","",'Payroll Entry'!$G$10) | E11: =IF($J11="","",'Payroll Entry'!$G$11) | F11: =IF('Payroll Entry'!A32="","",'Payroll Entry'!A32) | G11: =IF('Payroll Entry'!B32="","",'Payroll Entry'!B32) | H11: =IF('Payroll Entry'!C32="","",'Payroll Entry'!C32) | I11: =IF('Payroll Entry'!D32="","",'Payroll Entry'!D32) | J11: =IF('Payroll Entry'!$E32="","",'Payroll Entry'!E32) | K11: =IF('Payroll Entry'!$E32="","",'Payroll Entry'!F32) | L11: =IF('Payroll Entry'!$E32="","",'Payroll Entry'!G32) | M11: =IF('Payroll Entry'!$E32="","",'Payroll Entry'!H32) | N11: =IF('Payroll Entry'!$E32="","",'Payroll Entry'!I32) | O11: =IF($J11="","","Self Reporter") | P11: =IF($J11="","","Pay Types")
A12: =IF($J12="","",'Payroll Entry'!$G$4) | B12: =IF($J12="","",'Payroll Entry'!$G$5) | C12: =IF($J12="","",'Payroll Entry'!$G$9) | D12: =IF($J12="","",'Payroll Entry'!$G$10) | E12: =IF($J12="","",'Payroll Entry'!$G$11) | F12: =IF('Payroll Entry'!A33="","",'Payroll Entry'!A33) | G12: =IF('Payroll Entry'!B33="","",'Payroll Entry'!B33) | H12: =IF('Payroll Entry'!C33="","",'Payroll Entry'!C33) | I12: =IF('Payroll Entry'!D33="","",'Payroll Entry'!D33) | J12: =IF('Payroll Entry'!$E33="","",'Payroll Entry'!E33) | K12: =IF('Payroll Entry'!$E33="","",'Payroll Entry'!F33) | L12: =IF('Payroll Entry'!$E33="","",'Payroll Entry'!G33) | M12: =IF('Payroll Entry'!$E33="","",'Payroll Entry'!H33) | N12: =IF('Payroll Entry'!$E33="","",'Payroll Entry'!I33) | O12: =IF($J12="","","Self Reporter") | P12: =IF($J12="","","Pay Types")
A13: =IF($J13="","",'Payroll Entry'!$G$4) | B13: =IF($J13="","",'Payroll Entry'!$G$5) | C13: =IF($J13="","",'Payroll Entry'!$G$9) | D13: =IF($J13="","",'Payroll Entry'!$G$10) | E13: =IF($J13="","",'Payroll Entry'!$G$11) | F13: =IF('Payroll Entry'!A34="","",'Payroll Entry'!A34) | G13: =IF('Payroll Entry'!B34="","",'Payroll Entry'!B34) | H13: =IF('Payroll Entry'!C34="","",'Payroll Entry'!C34) | I13: =IF('Payroll Entry'!D34="","",'Payroll Entry'!D34) | J13: =IF('Payroll Entry'!$E34="","",'Payroll Entry'!E34) | K13: =IF('Payroll Entry'!$E34="","",'Payroll Entry'!F34) | L13: =IF('Payroll Entry'!$E34="","",'Payroll Entry'!G34) | M13: =IF('Payroll Entry'!$E34="","",'Payroll Entry'!H34) | N13: =IF('Payroll Entry'!$E34="","",'Payroll Entry'!I34) | O13: =IF($J13="","","Self Reporter") | P13: =IF($J13="","","Pay Types")
A14: =IF($J14="","",'Payroll Entry'!$G$4) | B14: =IF($J14="","",'Payroll Entry'!$G$5) | C14: =IF($J14="","",'Payroll Entry'!$G$9) | D14: =IF($J14="","",'Payroll Entry'!$G$10) | E14: =IF($J14="","",'Payroll Entry'!$G$11) | F14: =IF('Payroll Entry'!A35="","",'Payroll Entry'!A35) | G14: =IF('Payroll Entry'!B35="","",'Payroll Entry'!B35) | H14: =IF('Payroll Entry'!C35="","",'Payroll Entry'!C35) | I14: =IF('Payroll Entry'!D35="","",'Payroll Entry'!D35) | J14: =IF('Payroll Entry'!$E35="","",'Payroll Entry'!E35) | K14: =IF('Payroll Entry'!$E35="","",'Payroll Entry'!F35) | L14: =IF('Payroll Entry'!$E35="","",'Payroll Entry'!G35) | M14: =IF('Payroll Entry'!$E35="","",'Payroll Entry'!H35) | N14: =IF('Payroll Entry'!$E35="","",'Payroll Entry'!I35) | O14: =IF($J14="","","Self Reporter") | P14: =IF($J14="","","Pay Types")
A15: =IF($J15="","",'Payroll Entry'!$G$4) | B15: =IF($J15="","",'Payroll Entry'!$G$5) | C15: =IF($J15="","",'Payroll Entry'!$G$9) | D15: =IF($J15="","",'Payroll Entry'!$G$10) | E15: =IF($J15="","",'Payroll Entry'!$G$11) | F15: =IF('Payroll Entry'!A36="","",'Payroll Entry'!A36) | G15: =IF('Payroll Entry'!B36="","",'Payroll Entry'!B36) | H15: =IF('Payroll Entry'!C36="","",'Payroll Entry'!C36) | I15: =IF('Payroll Entry'!D36="","",'Payroll Entry'!D36) | J15: =IF('Payroll Entry'!$E36="","",'Payroll Entry'!E36) | K15: =IF('Payroll Entry'!$E36="","",'Payroll Entry'!F36) | L15: =IF('Payroll Entry'!$E36="","",'Payroll Entry'!G36) | M15: =IF('Payroll Entry'!$E36="","",'Payroll Entry'!H36) | N15: =IF('Payroll Entry'!$E36="","",'Payroll Entry'!I36) | O15: =IF($J15="","","Self Reporter") | P15: =IF($J15="","","Pay Types")
A16: =IF($J16="","",'Payroll Entry'!$G$4) | B16: =IF($J16="","",'Payroll Entry'!$G$5) | C16: =IF($J16="","",'Payroll Entry'!$G$9) | D16: =IF($J16="","",'Payroll Entry'!$G$10) | E16: =IF($J16="","",'Payroll Entry'!$G$11) | F16: =IF('Payroll Entry'!A37="","",'Payroll Entry'!A37) | G16: =IF('Payroll Entry'!B37="","",'Payroll Entry'!B37) | H16: =IF('Payroll Entry'!C37="","",'Payroll Entry'!C37) | I16: =IF('Payroll Entry'!D37="","",'Payroll Entry'!D37) | J16: =IF('Payroll Entry'!$E37="","",'Payroll Entry'!E37) | K16: =IF('Payroll Entry'!$E37="","",'Payroll Entry'!F37) | L16: =IF('Payroll Entry'!$E37="","",'Payroll Entry'!G37) | M16: =IF('Payroll Entry'!$E37="","",'Payroll Entry'!H37) | N16: =IF('Payroll Entry'!$E37="","",'Payroll Entry'!I37) | O16: =IF($J16="","","Self Reporter") | P16: =IF($J16="","","Pay Types")
A17: =IF($J17="","",'Payroll Entry'!$G$4) | B17: =IF($J17="","",'Payroll Entry'!$G$5) | C17: =IF($J17="","",'Payroll Entry'!$G$9) | D17: =IF($J17="","",'Payroll Entry'!$G$10) | E17: =IF($J17="","",'Payroll Entry'!$G$11) | F17: =IF('Payroll Entry'!A38="","",'Payroll Entry'!A38) | G17: =IF('Payroll Entry'!B38="","",'Payroll Entry'!B38) | H17: =IF('Payroll Entry'!C38="","",'Payroll Entry'!C38) | I17: =IF('Payroll Entry'!D38="","",'Payroll Entry'!D38) | J17: =IF('Payroll Entry'!$E38="","",'Payroll Entry'!E38) | K17: =IF('Payroll Entry'!$E38="","",'Payroll Entry'!F38) | L17: =IF('Payroll Entry'!$E38="","",'Payroll Entry'!G38) | M17: =IF('Payroll Entry'!$E38="","",'Payroll Entry'!H38) | N17: =IF('Payroll Entry'!$E38="","",'Payroll Entry'!I38) | O17: =IF($J17="","","Self Reporter") | P17: =IF($J17="","","Pay Types")
... A501: =IF($J501="","",'Payroll Entry'!$G$4) | B501: =IF($J501="","",'Payroll Entry'!$G$5) | C501: =IF($J501="","",'Payroll Entry'!$G$9) | D501: =IF($J501="","",'Payroll Entry'!$G$10) | E501: =IF($J501="","",'Payroll Entry'!$G$11) | F501: =IF('Payroll Entry'!A522="","",'Payroll Entry'!A522) | G501: =IF('Payroll Entry'!B522="","",'Payroll Entry'!B522) | H501: =IF('Payroll Entry'!C522="","",'Payroll Entry'!C522) | I501: =IF('Payroll Entry'!D522="","",'Payroll Entry'!D522) | J501: =IF('Payroll Entry'!$E522="","",'Payroll Entry'!E522) | K501: =IF('Payroll Entry'!$E522="","",'Payroll Entry'!F522) | L501: =IF('Payroll Entry'!$E522="","",'Payroll Entry'!G522) | M501: =IF('Payroll Entry'!$E522="","",'Payroll Entry'!H522) | N501: =IF('Payroll Entry'!$E522="","",'Payroll Entry'!I522) | O501: =IF($J501="","","Self Reporter") | P501: =IF($J501="","","Pay Types")

Sheet Inclusion-Exclusion Rules
A1: Inclusion/Exclusion Rules for Calculation of Subject Wages
A3: Below are some common guidelines to follow when reporting payroll for workers' compensation. Check for state exceptions.
A5: General Rules:
A6: Included in payroll to be reported
A7: Paid time off (PTO)
A8: Vacation pay
A9: Holiday pay
A10: Sick pay
A11: Bonuses
A12: Commissions
A13: Value of housing provided
A14: Value of meals provided by employer
... A26: State Exceptions:
A27: Arizona | B27: Exclude value of lodging and meals in payroll. Exclude Davis Bacon fringe benefit payments to ERISA qualified third party pension plan.
A28: California | B28: Exclude value of lodging and meals in payroll. Exclude employee contributions to Section 125 plan (except pension, deferred comp plan).
A29: Colorado | B29: Exclude Davis Bacon fringe benefits paid by employer.
A30: Florida | B30: Exclude awards for employee achievements or discoveries, pure gratuities or voluntary profit sharing.
A31: Kansas | B31: Exclude vacation, holiday or sick pay
A32: Kentucky | B32: Exclude payments for hand tools
A33: Louisiana | B33: Exclude awards for achievements or discovery, pure gratuities or voluntary profit sharing.
A34: Nevada | B34: Include overtime, tips, severance. Payroll limitation of $36,000 applies for all employees.
A35: New Jersey | B35: Include tips.
A36: New Mexico | B36: Exclude bonuses paid under state approved safety program.
A37: Oregon | B37: Exclude vacation or unanticipated bonus pay. Exclude Davis Bacon fringe benefits paid into ERISA quailed 3rd party pension plan.
A38: Pennsylvania | B38: Include overtime. Exclude rewards for discovery or invention.
... A40: Virginia | B40: Include all Davis Bacon wages, even when paid to 3rd party trusts.
